const_key.py
data_deal_util.py
debug_task.py
env_manager.py
es_util.py
git_util.py
git_util_dev.py
label_util.py
log_manager.py
operator_framework.py
operator_interface.py
redis_util.py
scene_util.py
evaluat/__init__.py
evaluat/const.py
evaluat/data_init_strategy.py
evaluat/data_util.py
evaluat/db_util.py
evaluat/logsim_data_init_strategy.py
evaluat/python_main.py
evaluat/sence_data_init_strategy.py
evaluat/source_data_init_strategy.py
evaluat/task_progress.py
util/__init__.py
util/data_utils.py
util/date_utils.py
util/db_module.py
util/db_utils.py
util/message_util.py
util/minio_client_singleton.py
util/nacos_client.py
util/obs_client_singleton.py
util/redis_client.py
util/redis_module.py
util/token_utils.py
eval_sdk-0.2.7.dist-info/METADATA
eval_sdk-0.2.7.dist-info/WHEEL
eval_sdk-0.2.7.dist-info/top_level.txt
eval_sdk-0.2.7.dist-info/RECORD
